st_cytoscape/__init__.py
st_cytoscape/frontend/build/asset-manifest.json
st_cytoscape/frontend/build/bootstrap.min.css
st_cytoscape/frontend/build/index.html
st_cytoscape/frontend/build/precache-manifest.5e2117b64c6bd0d320b69481c38405b6.js
st_cytoscape/frontend/build/precache-manifest.6566f95ef1b49eb1c661d972e2c3ce94.js
st_cytoscape/frontend/build/service-worker.js
st_cytoscape/frontend/build/static/js/2.1c93493d.chunk.js
st_cytoscape/frontend/build/static/js/2.1c93493d.chunk.js.LICENSE.txt
st_cytoscape/frontend/build/static/js/2.1c93493d.chunk.js.map
st_cytoscape/frontend/build/static/js/2.b5e4971c.chunk.js
st_cytoscape/frontend/build/static/js/2.b5e4971c.chunk.js.LICENSE.txt
st_cytoscape/frontend/build/static/js/2.b5e4971c.chunk.js.map
st_cytoscape/frontend/build/static/js/main.25e00619.chunk.js
st_cytoscape/frontend/build/static/js/main.25e00619.chunk.js.map
st_cytoscape/frontend/build/static/js/main.8125c52f.chunk.js
st_cytoscape/frontend/build/static/js/main.8125c52f.chunk.js.map
st_cytoscape/frontend/build/static/js/runtime-main.db64ee98.js
st_cytoscape/frontend/build/static/js/runtime-main.db64ee98.js.map
st_cytoscape-0.0.5.dist-info/LICENSE
st_cytoscape-0.0.5.dist-info/METADATA
st_cytoscape-0.0.5.dist-info/WHEEL
st_cytoscape-0.0.5.dist-info/top_level.txt
st_cytoscape-0.0.5.dist-info/RECORD
