Metadata-Version: 2.1
Name: st-cytoscape
Version: 0.0.5
Summary: A Streamlit component to display a Cytoscape.js graph
Home-page: UNKNOWN
Author: 
Author-email: 
License: UNKNOWN
Platform: UNKNOWN
Requires-Python: >=3.6
License-File: LICENSE
Requires-Dist: streamlit (>=0.63)
